{"nodes": [{"id": "spec_06_odlozone_poza_mvp", "label": "docs/spec/06-odlozone-poza-mvp.md \u2014 Od\u0142o\u017cone poza MVP", "file_type": "document", "source_file": "docs/spec/06-odlozone-poza-mvp.md", "source_location": null, "source_url": null, "captured_at": null, "author": null, "contributor": null}], "edges": [{"source": "spec_06_odlozone_poza_mvp", "target": "entity_group_change_request", "relation": "references", "confidence": "EXTRACTED", "confidence_score": 1.0, "source_file": "docs/spec/06-odlozone-poza-mvp.md", "source_location": null, "weight": 1.0}, {"source": "spec_06_odlozone_poza_mvp", "target": "concept_notification_center_domain", "relation": "references", "confidence": "EXTRACTED", "confidence_score": 1.0, "source_file": "docs/spec/06-odlozone-poza-mvp.md", "source_location": null, "weight": 1.0}, {"source": "spec_06_odlozone_poza_mvp", "target": "decision_standard_connect", "relation": "references", "confidence": "EXTRACTED", "confidence_score": 1.0, "source_file": "docs/spec/06-odlozone-poza-mvp.md", "source_location": null, "weight": 1.0}], "hyperedges": []}